env_excavator-1.5.0.dist-info/DESCRIPTION.rst
env_excavator-1.5.0.dist-info/METADATA
env_excavator-1.5.0.dist-info/metadata.json
env_excavator-1.5.0.dist-info/RECORD
env_excavator-1.5.0.dist-info/top_level.txt
env_excavator-1.5.0.dist-info/WHEEL
excavator/__init__.py
excavator/utils.py
