Metadata-Version: 2.0
Name: env-excavator
Version: 1.5.0
Summary: Tools for exconverting environment variables to native python objects
Home-page: https://github.com/simpleenergy/env-excavator
Author: Piper Merriam
Author-email: piper@simpleenergy.com
License: MIT
Keywords: env-excavator
Platform: UNKNOWN
Classifier: Development Status :: 2 - Pre-Alpha
Classifier: Intended Audience :: Developers
Classifier: License :: OSI Approved :: BSD License
Classifier: Natural Language :: English
Classifier: Programming Language :: Python :: 2
Classifier: Programming Language :: Python :: 2.6
Classifier: Programming Language :: Python :: 2.7
Classifier: Programming Language :: Python :: 3
Classifier: Programming Language :: Python :: 3.4
Classifier: Programming Language :: Python :: 3.5
